LICENSE
README.md
setup.py
ChatTTS/__init__.py
ChatTTS/core.py
ChatTTS/norm.py
ChatTTS/config/__init__.py
ChatTTS/config/config.py
ChatTTS/model/__init__.py
ChatTTS/model/dvae.py
ChatTTS/model/embed.py
ChatTTS/model/gpt.py
ChatTTS/model/processors.py
ChatTTS/model/speaker.py
ChatTTS/model/tokenizer.py
ChatTTS/model/cuda/__init__.py
ChatTTS/model/cuda/patch.py
ChatTTS/model/cuda/te_llama.py
ChatTTS/model/velocity/__init__.py
ChatTTS/model/velocity/block_manager.py
ChatTTS/model/velocity/configs.py
ChatTTS/model/velocity/llama.py
ChatTTS/model/velocity/llm.py
ChatTTS/model/velocity/llm_engine.py
ChatTTS/model/velocity/model_loader.py
ChatTTS/model/velocity/model_runner.py
ChatTTS/model/velocity/output.py
ChatTTS/model/velocity/sampler.py
ChatTTS/model/velocity/sampling_params.py
ChatTTS/model/velocity/scheduler.py
ChatTTS/model/velocity/sequence.py
ChatTTS/model/velocity/worker.py
ChatTTS/res/__init__.py
ChatTTS/res/homophones_map.json
ChatTTS/res/sha256_map.json
ChatTTS/utils/__init__.py
ChatTTS/utils/dl.py
ChatTTS/utils/gpu.py
ChatTTS/utils/io.py
ChatTTS/utils/log.py
chattts.egg-info/PKG-INFO
chattts.egg-info/SOURCES.txt
chattts.egg-info/dependency_links.txt
chattts.egg-info/requires.txt
chattts.egg-info/top_level.txt