Metadata-Version: 2.2
Name: chattts
Version: 0.2.2
Summary: A generative speech model for daily dialogue
Home-page: https://github.com/2noise/ChatTTS
Author: 2noise
Author-email: open-source@2noise.com
Maintainer: fumiama
License: AGPLv3+
Platform: any
Classifier: Programming Language :: Python :: 3
Classifier: Operating System :: OS Independent
Classifier: License :: OSI Approved :: GNU Affero General Public License v3 or later (AGPLv3+)
License-File: LICENSE
Requires-Dist: numba
Requires-Dist: numpy<2.0.0
Requires-Dist: pybase16384
Requires-Dist: torch>=2.1.0
Requires-Dist: torchaudio
Requires-Dist: tqdm
Requires-Dist: transformers>=4.41.1
Requires-Dist: vector_quantize_pytorch
Requires-Dist: vocos
Dynamic: author
Dynamic: author-email
Dynamic: classifier
Dynamic: description
Dynamic: description-content-type
Dynamic: home-page
Dynamic: license
Dynamic: maintainer
Dynamic: platform
Dynamic: requires-dist
Dynamic: summary
